decoupler/_Method.py
decoupler/_Plotter.py
decoupler/__init__.py
decoupler/_datatype.py
decoupler/_docs.py
decoupler/_download.py
decoupler/_log.py
decoupler/_odeps.py
decoupler/bm/__init__.py
decoupler/bm/_pp.py
decoupler/bm/_run.py
decoupler/bm/metric/_Metric.py
decoupler/bm/metric/__init__.py
decoupler/bm/metric/_auc.py
decoupler/bm/metric/_fscore.py
decoupler/bm/metric/_hmean.py
decoupler/bm/metric/_qrank.py
decoupler/bm/pl/__init__.py
decoupler/bm/pl/_auc.py
decoupler/bm/pl/_bar.py
decoupler/bm/pl/_format.py
decoupler/bm/pl/_fscore.py
decoupler/bm/pl/_qrank.py
decoupler/bm/pl/_summary.py
decoupler/ds/__init__.py
decoupler/ds/_bulk.py
decoupler/ds/_scell.py
decoupler/ds/_spatial.py
decoupler/ds/_toy.py
decoupler/ds/_utils.py
decoupler/mt/__init__.py
decoupler/mt/_aucell.py
decoupler/mt/_consensus.py
decoupler/mt/_decouple.py
decoupler/mt/_gsea.py
decoupler/mt/_gsva.py
decoupler/mt/_mdt.py
decoupler/mt/_methods.py
decoupler/mt/_mlm.py
decoupler/mt/_ora.py
decoupler/mt/_pv.py
decoupler/mt/_query_set.py
decoupler/mt/_run.py
decoupler/mt/_udt.py
decoupler/mt/_ulm.py
decoupler/mt/_viper.py
decoupler/mt/_waggr.py
decoupler/mt/_zscore.py
decoupler/op/__init__.py
decoupler/op/_collectri.py
decoupler/op/_dorothea.py
decoupler/op/_dtype.py
decoupler/op/_hallmark.py
decoupler/op/_progeny.py
decoupler/op/_resource.py
decoupler/op/_translate.py
decoupler/pl/__init__.py
decoupler/pl/_barplot.py
decoupler/pl/_dotplot.py
decoupler/pl/_filter_by_expr.py
decoupler/pl/_filter_by_prop.py
decoupler/pl/_filter_samples.py
decoupler/pl/_leading_edge.py
decoupler/pl/_network.py
decoupler/pl/_obsbar.py
decoupler/pl/_obsm.py
decoupler/pl/_order.py
decoupler/pl/_order_targets.py
decoupler/pl/_source_targets.py
decoupler/pl/_volcano.py
decoupler/pp/__init__.py
decoupler/pp/anndata.py
decoupler/pp/data.py
decoupler/pp/net.py
decoupler/tl/__init__.py
decoupler/tl/_rankby_group.py
decoupler/tl/_rankby_obsm.py
decoupler/tl/_rankby_order.py
decoupler-2.1.4.dist-info/METADATA
decoupler-2.1.4.dist-info/WHEEL
decoupler-2.1.4.dist-info/licenses/LICENSE
decoupler-2.1.4.dist-info/RECORD
