Metadata-Version: 2.4
Name: decoupler
Version: 2.1.4
Summary: Python package to perform enrichment analysis from omics data.
Project-URL: Documentation, https://decoupler.readthedocs.io/
Project-URL: Homepage, https://github.com/scverse/decoupler
Project-URL: Source, https://github.com/scverse/decoupler
Author: Pau Badia i Mompel
Maintainer-email: Pau Badia i Mompel <paubim@stanford.edu>
License: BSD 3-Clause License
License-File: LICENSE
Classifier: Programming Language :: Python :: 3 :: Only
Classifier: Programming Language :: Python :: 3.10
Classifier: Programming Language :: Python :: 3.11
Classifier: Programming Language :: Python :: 3.12
Classifier: Programming Language :: Python :: 3.13
Classifier: Programming Language :: Python :: 3.14
Requires-Python: >=3.10
Requires-Dist: adjusttext
Requires-Dist: anndata
Requires-Dist: docrep
Requires-Dist: marsilea
Requires-Dist: numba
Requires-Dist: requests
Requires-Dist: scipy
Requires-Dist: session-info2
Requires-Dist: tqdm
Provides-Extra: dev
Requires-Dist: pre-commit; extra == 'dev'
Requires-Dist: twine>=4.0.2; extra == 'dev'
Provides-Extra: doc
Requires-Dist: docutils!=0.18.*,!=0.19.*,>=0.8; extra == 'doc'
Requires-Dist: ipykernel; extra == 'doc'
Requires-Dist: ipython; extra == 'doc'
Requires-Dist: myst-nb>=1.1; extra == 'doc'
Requires-Dist: pandas; extra == 'doc'
Requires-Dist: setuptools; extra == 'doc'
Requires-Dist: sphinx-autodoc-typehints; extra == 'doc'
Requires-Dist: sphinx-book-theme>=1; extra == 'doc'
Requires-Dist: sphinx-copybutton; extra == 'doc'
Requires-Dist: sphinx-tabs; extra == 'doc'
Requires-Dist: sphinx>=8.1; extra == 'doc'
Requires-Dist: sphinxcontrib-bibtex>=1; extra == 'doc'
Requires-Dist: sphinxext-opengraph; extra == 'doc'
Provides-Extra: full
Requires-Dist: dcor; extra == 'full'
Requires-Dist: igraph; extra == 'full'
Requires-Dist: ipywidgets; extra == 'full'
Requires-Dist: pydeseq2; extra == 'full'
Requires-Dist: scanpy; extra == 'full'
Requires-Dist: xgboost; extra == 'full'
Provides-Extra: test
Requires-Dist: coverage>=7.10; extra == 'test'
Requires-Dist: dcor; extra == 'test'
Requires-Dist: gseapy; extra == 'test'
Requires-Dist: igraph; extra == 'test'
Requires-Dist: ipywidgets; extra == 'test'
Requires-Dist: memory-profiler; extra == 'test'
Requires-Dist: pydeseq2; extra == 'test'
Requires-Dist: pytest; extra == 'test'
Requires-Dist: pytest-cov; extra == 'test'
Requires-Dist: scanpy; extra == 'test'
Requires-Dist: statsmodels; extra == 'test'
Requires-Dist: xgboost; extra == 'test'
